Z0Z_tools/__init__.py
Z0Z_tools/amplitude.py
Z0Z_tools/autoRevert.py
Z0Z_tools/clippingArrays.py
Z0Z_tools/filesystemToolkit.py
Z0Z_tools/ioAudio.py
Z0Z_tools/optionalPyTorch.py
Z0Z_tools/pipAnything.py
Z0Z_tools/py.typed
Z0Z_tools/scipyDOTsignalDOT_short_time_fft.py
Z0Z_tools/theTypes.py
Z0Z_tools/windowingFunctions.py
astTransformations/__init__.py
astTransformations/windowingFunctions.py
tests/__init__.py
tests/conftest.py
tests/conftestCoping.py
tests/test_amplitude.py
tests/test_clippingArrays.py
tests/test_filesystemToolbox.py
tests/test_pipAnything.py
tests/test_spectrogram.py
tests/test_waveform.py
tests/test_windowingFunctions.py
z0z_tools-1.0.1.dist-info/licenses/LICENSE
z0z_tools-1.0.1.dist-info/METADATA
z0z_tools-1.0.1.dist-info/WHEEL
z0z_tools-1.0.1.dist-info/top_level.txt
z0z_tools-1.0.1.dist-info/RECORD
