Metadata-Version: 2.4
Name: Z0Z_tools
Version: 1.0.1
Summary: Tools for audio/signal processing and package management.
Author-email: Hunter Hogan <HunterHogan@pm.me>
License: CC-BY-NC-4.0
Project-URL: Donate, https://www.patreon.com/integrated
Project-URL: Homepage, https://github.com/hunterhogan/Z0Z_tools
Project-URL: Issues, https://github.com/hunterhogan/Z0Z_tools/issues
Project-URL: Repository, https://github.com/hunterhogan/Z0Z_tools.git
Keywords: Python,development,tools
Classifier: Development Status :: 5 - Production/Stable
Classifier: Environment :: Console
Classifier: Framework :: Pytest
Classifier: Intended Audience :: Developers
Classifier: Intended Audience :: Education
Classifier: Intended Audience :: End Users/Desktop
Classifier: Intended Audience :: Other Audience
Classifier: Intended Audience :: Science/Research
Classifier: Natural Language :: English
Classifier: Operating System :: OS Independent
Classifier: Programming Language :: Python
Classifier: Programming Language :: Python :: 3
Classifier: Programming Language :: Python :: 3.10
Classifier: Programming Language :: Python :: 3.11
Classifier: Programming Language :: Python :: 3.12
Classifier: Programming Language :: Python :: 3.13
Classifier: Topic :: Multimedia :: Sound/Audio
Classifier: Topic :: Multimedia :: Sound/Audio :: Analysis
Classifier: Topic :: Multimedia :: Sound/Audio :: Conversion
Classifier: Topic :: Multimedia :: Sound/Audio :: Editors
Classifier: Topic :: Scientific/Engineering
Classifier: Topic :: Scientific/Engineering :: Artificial Intelligence
Classifier: Topic :: Scientific/Engineering :: Information Analysis
Classifier: Topic :: Scientific/Engineering :: Mathematics
Classifier: Topic :: Scientific/Engineering :: Physics
Classifier: Topic :: System :: Filesystems
Classifier: Topic :: System :: Installation/Setup
Classifier: Topic :: Text Processing
Classifier: Topic :: Utilities
Classifier: Typing :: Typed
Requires-Python: >=3.10
License-File: LICENSE
Requires-Dist: hunterMakesPy
Requires-Dist: numpy
Requires-Dist: packaging
Requires-Dist: resampy
Requires-Dist: scipy
Requires-Dist: soundfile
Requires-Dist: tqdm
Provides-Extra: pytorch
Requires-Dist: torch; extra == "pytorch"
Provides-Extra: testing
Requires-Dist: astToolkit; extra == "testing"
Requires-Dist: mypy; extra == "testing"
Requires-Dist: pandas; extra == "testing"
Requires-Dist: pytest-cov; extra == "testing"
Requires-Dist: pytest-mock; extra == "testing"
Requires-Dist: pytest-xdist; extra == "testing"
Requires-Dist: pytest; extra == "testing"
Requires-Dist: pyupgrade; extra == "testing"
Requires-Dist: scipy-stubs; extra == "testing"
Requires-Dist: setuptools-scm; extra == "testing"
Requires-Dist: torch; extra == "testing"
Requires-Dist: trove_classifiers; extra == "testing"
Dynamic: license-file
